pySynaptics/__init__.py
pySynaptics/pySynaptics.py
pySynaptics/lib/csynaptics.so
pySynaptics-0.0.1.dist-info/METADATA
pySynaptics-0.0.1.dist-info/WHEEL
pySynaptics-0.0.1.dist-info/top_level.txt
pySynaptics-0.0.1.dist-info/RECORD
