Metadata-Version: 2.1
Name: pySynaptics
Version: 0.0.1
Summary: Python module for Synaptics touchpad and fingerprint sensors
Home-page: https://github.com/
Author: Vincent Huang
Author-email: vincenthsw@gmail.com
Classifier: Programming Language :: Python :: 3
Classifier: License :: OSI Approved :: MIT License
Classifier: Operating System :: OS Independent
Requires-Python: >=3.6
